{
    "31441100": {
        "FusionConfiguration": {
            "communication_parameters": {
                "CommunicationParameters": {
                    "communication_type": "INTRA PROCESS",
                    "ip_add": "",
                    "ip_port": 0
                }
            },
            "input_type": {
                "InputType": {
                    "input_type_conf": "31441100",
                    "input_type_conf_right": "0",
                    "input_type_input": "AUTO",
                    "input_virtual_serial_number": 0
                }
            },
            "override_gravity": false,
            "pose": "1.000000 0.000000 0.000000 0.000000 0.000000 1.000000 0.000000 -1.125080 0.000000 0.000000 1.000000 0.000000 0.000000 0.000000 0.000000 1.000000",
            "serial_number": 31441100
        }
    },
    "37130122": {
        "FusionConfiguration": {
            "communication_parameters": {
                "CommunicationParameters": {
                    "communication_type": "INTRA PROCESS",
                    "ip_add": "",
                    "ip_port": 0
                }
            },
            "input_type": {
                "InputType": {
                    "input_type_conf": "37130122",
                    "input_type_conf_right": "0",
                    "input_type_input": "AUTO",
                    "input_virtual_serial_number": 0
                }
            },
            "override_gravity": false,
            "pose": "0.028503 0.031975 0.999082 -2.585489 0.028445 0.999058 -0.032786 -0.868406 -0.999189 0.029354 0.027566 2.806319 0.000000 0.000000 0.000000 1.000000",
            "serial_number": 37130122
        }
    }
}
